{
    "台灣_報導者@twreporter": "https://www.twreporter.org/a/rss2.xml",
	"台灣_公共電視@pts": "https://news.pts.org.tw/xml/newsfeed.xml",
    "德國_德國之聲@dw": "https://rss.dw.com/xml/podcast_radio_china",
    "香港_眾新聞@hkcnews": "https://www.hkcnews.com/rss.xml",
	"香港_立場新聞@thestandnews": "https://www.thestandnews.com/rss/",
	"香港_端傳媒@theinitium": "https://www.theinitium.com/newsfeed/",
	"法國_法廣@rfi": "https://www.rfi.fr/tw/rss",
	"台灣_關鍵評論網_國際@tnlIntl": "https://feeds.feedburner.com/TheNewsLensINTL",
	"英國_英國廣播公司@bbc": "https://feeds.bbci.co.uk/zhongwen/trad/rss.xml",
	"香港_香港電台_國際@rthkIntl": "https://www.rthk.hk/rthk/news/rss/c_expressnews_cinternational.xml",
	"香港_香港電台_中國@rthkCN": "https://www.rthk.hk/rthk/news/rss/c_expressnews_greaterchina.xml",
	"韓國_KBS_國際@kbsIntl": "http://world.kbs.co.kr/rss/rss_news.htm?lang=c&id=In",
	"韓國_KBS_南北韓@kbsIK": "http://world.kbs.co.kr/rss/rss_news.htm?lang=c&id=IK",
	"韓國_KBS_本週焦點@kbsHOT": "http://world.kbs.co.kr/rss/rss_hotissue.htm?lang=c"
}